Workbook

Sheet Sales_Data
A1: Order ID | B1: Order Date | C1: Customer Name | D1: City | E1: Category | F1: Product Name | G1: Order Status | H1: Unit Price | I1: Quantity | J1: Payment Mode | K1: Discount % | L1: Profit | M1: Total Sales
A2: 1001 | B2: 45294 | C2: Rahul Sharma | D2: Hyderabad | E2: Electronics | F2: Wireless Mouse | G2: Delivered | H2: 799 | I2: 2 | J2: UPI | K2: 5 | L2: 350 | M2: =Sales_Data!$H2*Sales_Data!$I2 -> 1598
A3: 1002 | B3: 45296 | C3: Pooja Verma | D3: Bangalore | E3: Electronics | F3: Keyboard | G3: Delivered | H3: 1299 | I3: 1 | J3: COD | K3: 0 | L3: 280 | M3: =Sales_Data!$H3*Sales_Data!$I3 -> 1299
A4: 1003 | B4: 45297 | C4: Amit Singh | D4: Delhi | E4: Fashion | F4: Sports Shoes | G4: Delivered | H4: 2499 | I4: 1 | J4: Card | K4: 10 | L4: 600 | M4: =Sales_Data!$H4*Sales_Data!$I4 -> 2499
A5: 1004 | B5: 45298 | C5: Komal Jain | D5: Mumbai | E5: Home Decor | F5: Table Lamp | G5: Delivered | H5: 999 | I5: 3 | J5: UPI | K5: 0 | L5: 720 | M5: =Sales_Data!$H5*Sales_Data!$I5 -> 2997
A6: 1005 | B6: 45299 | C6: Suresh Rao | D6: Pune | E6: Electronics | F6: Earbuds | G6: Returned | H6: 1499 | I6: 1 | J6: UPI | K6: 0 | L6: -149 | M6: =Sales_Data!$H6*Sales_Data!$I6 -> 1499
A7: 1006 | B7: 45300 | C7: Riya Gupta | D7: Kolkata | E7: Electronics | F7: Power Bank | G7: Delivered | H7: 1099 | I7: 2 | J7: Card | K7: 5 | L7: 460 | M7: =Sales_Data!$H7*Sales_Data!$I7 -> 2198
A8: 1007 | B8: 45300 | C8: Karan Mehta | D8: Chennai | E8: Fashion | F8: Men T-Shirt | G8: Delivered | H8: 599 | I8: 3 | J8: COD | K8: 0 | L8: 300 | M8: =Sales_Data!$H8*Sales_Data!$I8 -> 1797
A9: 1008 | B9: 45301 | C9: Deepak Kumar | D9: Hyderabad | E9: Home Decor | F9: Wall Clock | G9: Delivered | H9: 1299 | I9: 1 | J9: UPI | K9: 5 | L9: 250 | M9: =Sales_Data!$H9*Sales_Data!$I9 -> 1299
A10: 1009 | B10: 45302 | C10: Nikita Sharma | D10: Bangalore | E10: Fashion | F10: Handbag | G10: Delivered | H10: 1999 | I10: 1 | J10: Card | K10: 8 | L10: 450 | M10: =Sales_Data!$H10*Sales_Data!$I10 -> 1999
A11: 1010 | B11: 45303 | C11: Vishal Singh | D11: Mumbai | E11: Electronics | F11: Smartwatch | G11: Cancelled | H11: 2999 | I11: 1 | J11: UPI | K11: 0 | L11: 0 | M11: =Sales_Data!$H11*Sales_Data!$I11 -> 2999
A12: 1011 | B12: 45304 | C12: Harsh Patel | D12: Pune | E12: Home Decor | F12: Bedside Lamp | G12: Delivered | H12: 899 | I12: 2 | J12: COD | K12: 0 | L12: 380 | M12: =Sales_Data!$H12*Sales_Data!$I12 -> 1798
A13: 1012 | B13: 45305 | C13: Aisha Khan | D13: Delhi | E13: Electronics | F13: USB Cable | G13: Delivered | H13: 299 | I13: 4 | J13: UPI | K13: 0 | L13: 200 | M13: =Sales_Data!$H13*Sales_Data!$I13 -> 1196
... A51: 1050 | B51: 45339 | C51: Sunny Kumar | D51: Bangalore | E51: Home Decor | F51: Mirror | G51: Delivered | H51: 999 | I51: 1 | J51: UPI | K51: 5 | L51: 180 | M51: =Sales_Data!$H51*Sales_Data!$I51 -> 999
